dttk/data.py
dttk/features.py
dttk/__init__.py
dttk-0.0.3.dist-info/WHEEL
dttk-0.0.3.dist-info/METADATA
dttk-0.0.3.dist-info/RECORD
