Metadata-Version: 2.3
Name: dttk
Version: 0.0.3
Summary: A set of opinionated tools, code, and workflows for quick and dirty Machine Learning projects
Author: David Gasquez
Author-email: David Gasquez <davidgasquez@gmail.com>
Requires-Dist: altair>=5.5.0
Requires-Dist: httpx>=0.28.1
Requires-Dist: polars>=1.28.1
Requires-Dist: pyarrow>=20.0.0
Requires-Dist: scikit-learn>=1.6.1
Requires-Dist: skrub[transformers]>=0.5.3
Requires-Python: >=3.12
